eksma_optics_md_control/__init__.py
eksma_optics_md_control/_gui_base.py
eksma_optics_md_control/_version.py
eksma_optics_md_control/app.py
eksma_optics_md_control/gui.fbp
eksma_optics_md_control/main_frame.py
eksma_optics_md_control/main_panel.py
eksma_optics_md_control/task.py
eksma_optics_md_control/vendor/__init__.py
eksma_optics_md_control/vendor/serial/__init__.py
eksma_optics_md_control/vendor/serial/tools/__init__.py
eksma_optics_md_control/vendor/serial/tools/list_ports_windows.py
eksma_optics_md_control-0.1.7.dist-info/METADATA
eksma_optics_md_control-0.1.7.dist-info/WHEEL
eksma_optics_md_control-0.1.7.dist-info/entry_points.txt
eksma_optics_md_control-0.1.7.dist-info/licenses/LICENSE.txt
eksma_optics_md_control-0.1.7.dist-info/RECORD
