Metadata-Version: 2.4
Name: eksma-optics-md-control
Version: 0.1.7
Summary: EKSMA Optics Motorized Devices Controller
Project-URL: Homepage, https://eksmaoptics.com
Author-email: EKSMA Optics <info@eksmaoptics.com>
License-Expression: MIT
License-File: LICENSE.txt
Classifier: Development Status :: 4 - Beta
Classifier: Intended Audience :: Manufacturing
Classifier: Intended Audience :: Science/Research
Classifier: License :: OSI Approved :: MIT License
Classifier: Programming Language :: Python :: 3
Classifier: Programming Language :: Python :: 3.8
Classifier: Programming Language :: Python :: 3.9
Classifier: Programming Language :: Python :: 3.10
Classifier: Programming Language :: Python :: 3.11
Classifier: Programming Language :: Python :: 3.12
Classifier: Programming Language :: Python :: 3.13
Classifier: Topic :: Scientific/Engineering :: Interface Engine/Protocol Translator
Requires-Python: >=3.8
Requires-Dist: eksma-optics-motorized-devices[standard]>=0.1.3
Requires-Dist: wxpython>=4.2.2
